{
 "SoundBanksInfo": {
  "Platform": "Mac",
  "BasePlatform": "Mac",
  "SchemaVersion": "16",
  "SoundBankVersion": "154",
  "SoundBanks": [
   {
    "Id": "1639431926",
    "Type": "Event",
    "GUID": "{4CFC1F17-E90D-470B-B174-FA55AF8880FF}",
    "Language": "SFX",
    "Hash": "{11579D58-A992-47C2-864A-BEDDC15A5BE5}",
    "ObjectPath": "SFX_Ball",
    "ShortName": "SFX_Ball",
    "Path": "Event/SFX_Ball.bnk",
    "Media": [
     {
      "Id": "609893734",
      "Language": "SFX",
      "Streaming": "false",
      "Location": "Loose",
      "ShortName": "PH-SFX_Ball.wav",
      "Path": "Media/609893734.wem",
      "CachePath": "D7/{D7761E82-045D-7A2C-66A1-BFD4309E049B}.wem"
     }
    ],
    "Events": [
     {
      "Id": "1639431926",
      "Name": "SFX_Ball",
      "ObjectPath": "\\Events\\Default Work Unit\\SFX\\House\\SFX_Ball",
      "GUID": "{4CFC1F17-E90D-470B-B174-FA55AF8880FF}",
      "Color": "24",
      "DurationType": "OneShot",
      "DurationMin": "1.5198333",
      "DurationMax": "1.5198333",
      "MediaRefs": [
       {
        "Id": "609893734"
       }
      ]
     }
    ]
   }
  ],
  "FileHash": "{E9096896-6CFB-5186-C599-B9B8169D7B4C}"
 }
}